codec_versioning/__init__.py
codec_versioning/codec_versioning.py
codec_versioning-0.1.0.dist-info/licenses/LICENSE
codec_versioning-0.1.0.dist-info/licenses/LICENSE-CC0
codec_versioning-0.1.0.dist-info/METADATA
codec_versioning-0.1.0.dist-info/WHEEL
codec_versioning-0.1.0.dist-info/top_level.txt
codec_versioning-0.1.0.dist-info/RECORD
