Metadata-Version: 2.4
Name: codec-versioning
Version: 0.1.0
Summary: Manage multiple versions of general-purpose binary-based codecs.
Author-email: Emendir <dev@emendir.tech>
License-Expression: MIT-0 OR CC0-1.0
Classifier: Programming Language :: Python :: 3
Classifier: Operating System :: OS Independent
Requires-Python: >=3.6
License-File: LICENSE
License-File: LICENSE-CC0
Requires-Dist: brenthy_tools_beta
Dynamic: license-file
